genit/__init__.py
genit-0.35.dist-info/LICENSE
genit-0.35.dist-info/METADATA
genit-0.35.dist-info/WHEEL
genit-0.35.dist-info/top_level.txt
genit-0.35.dist-info/RECORD
